pyrometry/__init__.py
pyrometry/analysis.py
pyrometry/flamegraph.py
pyrometry/stats.py
pyrometry-0.0.2.dist-info/METADATA
pyrometry-0.0.2.dist-info/WHEEL
pyrometry-0.0.2.dist-info/licenses/LICENSE
pyrometry-0.0.2.dist-info/RECORD
