Metadata-Version: 2.4
Name: pyrometry
Version: 0.0.2
Summary: Flame graph comparison library
Project-URL: Documentation, https://github.com/p403n1x87/pyrometry#readme
Project-URL: Issues, https://github.com/p403n1x87/pyrometry/issues
Project-URL: Source, https://github.com/p403n1x87/pyrometry
Author-email: "Gabriele N. Tornetta" <gabriele.n.tornetta@gmail.com>
License-Expression: MIT
License-File: LICENSE
Classifier: Development Status :: 4 - Beta
Classifier: Programming Language :: Python
Classifier: Programming Language :: Python :: 3.8
Classifier: Programming Language :: Python :: 3.9
Classifier: Programming Language :: Python :: 3.10
Classifier: Programming Language :: Python :: 3.11
Classifier: Programming Language :: Python :: 3.12
Classifier: Programming Language :: Python :: 3.13
Classifier: Programming Language :: Python :: Implementation :: CPython
Classifier: Programming Language :: Python :: Implementation :: PyPy
Requires-Python: >=3.8
Requires-Dist: numpy
Requires-Dist: scipy
